basics/dff.v

`timescale 1ns / 1ps

module dff #(
    parameter Width = 1
) (
    input clk_i,
    input rst_ni,
    input [Width-1 : 0] i,
    output reg [Width-1 : 0] o
);

  always @(posedge clk_i or negedge rst_ni) begin
    if (!rst_ni) begin
      o <= 0;
    end else begin
      o <= i;
    end
  end
endmodule


module tb_dff;

  localparam WIDTH = 4;

  reg clk_i;
  reg rst_ni;
  reg [WIDTH-1 : 0] i;
  wire [WIDTH-1 : 0] o;

  dff #(
      .Width(WIDTH)
  ) uut (
      .clk_i(clk_i),
      .rst_ni(rst_ni),
      .i(i),
      .o(o)
  );

  always #5 clk_i <= ~clk_i;

  initial begin
    $dumpfile("tb_dff.vcd");
    $dumpvars(0, tb_dff);
    clk_i <= 0;
    rst_ni <= 0;
    i <= 4'h5;
    #1 rst_ni <= 1;
    #9 i <= 4'h7;
    #3 i <= 4'h9;
    #4 i <= 4'h2;
    #2 i <= 4'h6;
    #5 i <= 4'h3;
    #9 i <= 4'h4;
    $finish;
  end
endmodule

basics/tb_dff.vcd
$date
	Fri Aug 16 14:15:36 2024
$end
$version
	Icarus Verilog
$end
$timescale
	1ps
$end
$scope module tb_dff $end
$var wire 4 ! o [3:0] $end
$var reg 1 " clk_i $end
$var reg 4 # i [3:0] $end
$var reg 1 $ rst_ni $end
$scope module uut $end
$var wire 1 " clk_i $end
$var wire 4 % i [3:0] $end
$var wire 1 $ rst_ni $end
$var reg 4 & o [3:0] $end
$upscope $end
$upscope $end
$enddefinitions $end
#0
$dumpvars
b0 &
b101 %
0$
b101 #
0"
b0 !
$end
#1000
1$
#5000
b101 !
b101 &
1"
#10000
0"
b111 #
b111 %
#13000
b1001 #
b1001 %
#15000
b1001 !
b1001 &
1"
#17000
b10 #
b10 %
#19000
b110 #
b110 %
#20000
0"
#24000
b11 #
b11 %
#25000
b11 !
b11 &
1"
#30000
0"
#33000
b100 #
b100 %
