basics/shift_reg.v

`timescale 1ns / 1ps

module shift_reg #(
    parameter Width = 1,
    parameter Size  = 4
) (
    input clk_i,
    input we_i,
    input rst_ni,
    input [Width-1 : 0] data_i,
    output [Width-1 : 0] data_o
);

  integer size_c;
  reg [Width-1 : 0] mem[0 : Size-1];

  assign data_o = mem[Size-1];

  always @(posedge clk_i or negedge rst_ni) begin
    if (!rst_ni) begin
      for (size_c = 0; size_c < Size; size_c = size_c + 1) begin
        mem[size_c] <= 0;
      end
    end else if (we_i) begin
      mem[0] <= data_i;
      for (size_c = 1; size_c < Size; size_c = size_c + 1) begin
        mem[size_c] <= mem[size_c-1];
      end
    end
  end
endmodule


module tb_shift_reg;
  localparam WIDTH = 8;
  localparam SIZE = 3;
  reg clk;
  reg we_i;
  reg rst_ni;
  reg [WIDTH-1 : 0] data_i;
  wire [WIDTH-1 : 0] data_o;

  shift_reg #(
      .Width(WIDTH),
      .Size (SIZE)
  ) uut (
      .clk_i (clk),
      .we_i  (we_i),
      .rst_ni(rst_ni),
      .data_i(data_i),
      .data_o(data_o)
  );

  always #5 clk = ~clk;

  initial begin
    $dumpfile("tb_shift_reg.vcd");
    $dumpvars(0, tb_shift_reg);
    clk <= 0;
    we_i <= 0;
    data_i <= 8'hf0;
    rst_ni <= 0;
    #1 rst_ni <= 1;
    #13 we_i <= 1;
    #10 data_i <= 8'ha0;
    #10 we_i <= 0;
    #5 data_i <= 8'h80;
    we_i <= 1;
    #10 data_i <= 8'h60;
    #10 data_i <= 8'h49;
    #10 data_i <= 8'h20;
    rst_ni <= 0;
    #10 data_i <= 8'h15;
    #10 data_i <= 8'h19;
    rst_ni <= 1;
    #10 data_i <= 8'hc3;
    $finish;
  end
endmodule

basics/tb_shift_reg.vcd
$date
	Thu Aug 15 14:11:14 2024
$end
$version
	Icarus Verilog
$end
$timescale
	1ps
$end
$scope module tb_shift_reg $end
$var wire 8 ! data_o [7:0] $end
$var reg 1 " clk $end
$var reg 8 # data_i [7:0] $end
$var reg 1 $ rst_ni $end
$var reg 1 % we_i $end
$scope module uut $end
$var wire 1 " clk_i $end
$var wire 8 & data_i [7:0] $end
$var wire 8 ' data_o [7:0] $end
$var wire 1 $ rst_ni $end
$var wire 1 % we_i $end
$var integer 32 ( size_c [31:0] $end
$upscope $end
$upscope $end
$enddefinitions $end
#0
$dumpvars
b11 (
b0 '
b11110000 &
0%
0$
b11110000 #
0"
b0 !
$end
#1000
1$
#5000
1"
#10000
0"
#14000
1%
#15000
b11 (
1"
#20000
0"
#24000
b10100000 #
b10100000 &
#25000
b11 (
1"
#30000
0"
#34000
0%
#35000
1"
#39000
1%
b10000000 #
b10000000 &
#40000
0"
#45000
b11110000 !
b11110000 '
b11 (
1"
#49000
b1100000 #
b1100000 &
#50000
0"
#55000
b10100000 !
b10100000 '
b11 (
1"
#59000
b1001001 #
b1001001 &
#60000
0"
#65000
b10000000 !
b10000000 '
b11 (
1"
#69000
b0 !
b0 '
b11 (
0$
b100000 #
b100000 &
#70000
0"
#75000
b11 (
1"
#79000
b10101 #
b10101 &
#80000
0"
#85000
b11 (
1"
#89000
1$
b11001 #
b11001 &
#90000
0"
#95000
b11 (
1"
#99000
b11000011 #
b11000011 &
